cnode/__init__.py
cnode/node.py
cnode/nodepoint.py
cnode/pcnode.py
cnode/windows/32/libstar_python35.pyd
cnode/windows/32/libstar_python36.pyd
cnode/windows/32/libstar_python37.pyd
cnode/windows/32/libstar_python38.pyd
cnode/windows/32/libstar_python39.pyd
cnode/windows/32/libstarcore.dll
cnode/windows/32/libstarpy.pyd
cnode/windows/32/star_cnode.dll
cnode/windows/64/libstar_python35.pyd
cnode/windows/64/libstar_python36.pyd
cnode/windows/64/libstar_python37.pyd
cnode/windows/64/libstar_python38.pyd
cnode/windows/64/libstar_python39.pyd
cnode/windows/64/libstarcore.dll
cnode/windows/64/libstarpy.pyd
cnode/windows/64/star_cnode.dll
cnode-0.1.0.dist-info/METADATA
cnode-0.1.0.dist-info/WHEEL
cnode-0.1.0.dist-info/top_level.txt
cnode-0.1.0.dist-info/RECORD
