Metadata-Version: 2.1
Name: cnode
Version: 0.1.0
Summary: CNode is complex node, supports dynamic establishment and optimization of connections between nodes )
Home-page: https://github.com/srplab/cnode
Author: srplab
Author-email: srplab.cn@hotmail.com
License: MIT Licence
Keywords: network graph
Platform: any
Requires-Dist: requests
